{"totalItems": 1, "items": [{"kind": "books#volume", "volumeInfo": {"publisher": "McGraw-Hill/Irwin", "description": "This new Seventh Edition is designed for business students who are or who will soon become business professionals in the fast changing business world of today. The goal of this text is to help business students learn how to use and manage information technologies to revitalize business processes, improve business decision making, and gain competitive advantage. Thus it places a major emphasis on up-to-date coverage of the essential role of Internet technologies in providing a platform for business, commerce, and collaboration processes among all business stakeholders in today\u2019s networked enterprises and global markets. The benchmark text for the syllabus organized by technology, this text appraoches the material from a managerial perspective. O\u2019Brien defines technology and then explains how companies use the technology to improve performance. Real world cases finalize and enhance the explanation.", "language": "en", "publishedDate": "2005-01-14", "readingModes": {"text": false, "image": false}, "previewLink": "http://books.google.com/books?id=ClkfAQAAIAAJ&dq=isbn:007293588X&hl=&cd=1&source=gbs_api", "title": "Management Information Systems", "printType": "BOOK", "canonicalVolumeLink": "http://books.google.com/books/about/Management_Information_Systems.html?hl=&id=ClkfAQAAIAAJ", "pageCount": 624, "maturityRating": "NOT_MATURE", "contentVersion": "preview-1.0.0", "industryIdentifiers": [{"identifier": "UCSC:32106018076429", "type": "OTHER"}], "imageLinks": {"smallThumbnail": "http://books.google.com/books/content?id=ClkfAQAAIAAJ&printsec=frontcover&img=1&zoom=5&source=gbs_api", "thumbnail": "http://books.google.com/books/content?id=ClkfAQAAIAAJ&printsec=frontcover&img=1&zoom=1&source=gbs_api"}, "authors": ["James O'Brien", "George Marakas"], "ratingsCount": 2, "allowAnonLogging": false, "infoLink": "http://books.google.com/books?id=ClkfAQAAIAAJ&dq=isbn:007293588X&hl=&source=gbs_api", "categories": ["Computers"], "averageRating": 3.5}, "searchInfo": {"textSnippet": "This new Seventh Edition is designed for business students who are or who will soon become business professionals in the fast changing business world of today."}, "saleInfo": {"country": "US", "saleability": "NOT_FOR_SALE", "isEbook": false}, "etag": "gb9qJxP7A0A", "accessInfo": {"webReaderLink": "http://books.google.com/books/reader?id=ClkfAQAAIAAJ&hl=&printsec=frontcover&output=reader&source=gbs_api", "publicDomain": false, "embeddable": false, "country": "US", "textToSpeechPermission": "ALLOWED", "pdf": {"isAvailable": false}, "quoteSharingAllowed": false, "viewability": "NO_PAGES", "epub": {"isAvailable": false}, "accessViewStatus": "NONE"}, "id": "ClkfAQAAIAAJ", "selfLink": "https://www.googleapis.com/books/v1/volumes/ClkfAQAAIAAJ"}], "kind": "books#volumes"}