{"totalItems": 1, "items": [{"kind": "books#volume", "volumeInfo": {"publisher": "Pearson College Division", "subtitle": "Building, Measuring, and Managing Brand Equity", "description": "Incorporating the latest thinking and developments from both academia and industry, this exploration of brands, brand equity and strategic brand management combines a comprehensive theoretical foundation with numerous techniques and practical insights for making better day-to-day and long-term brand decisions. Focused on how-to and why, it provides specific tactical guidelines for planning, building, measuring and managing brand equity. It includes numerous examples on each topic and over 75 Branding Briefs that identify successful and unsuccessful brands.", "language": "en", "publishedDate": "2003", "readingModes": {"text": false, "image": false}, "previewLink": "http://books.google.com/books?id=lJaXQgAACAAJ&dq=isbn:0130411507&hl=&cd=1&source=gbs_api", "title": "Strategic Brand Management", "printType": "BOOK", "canonicalVolumeLink": "http://books.google.com/books/about/Strategic_Brand_Management.html?hl=&id=lJaXQgAACAAJ", "pageCount": 788, "maturityRating": "NOT_MATURE", "contentVersion": "preview-1.0.0", "industryIdentifiers": [{"identifier": "0130411507", "type": "ISBN_10"}, {"identifier": "9780130411501", "type": "ISBN_13"}], "imageLinks": {"smallThumbnail": "http://books.google.com/books/content?id=lJaXQgAACAAJ&printsec=frontcover&img=1&zoom=5&source=gbs_api", "thumbnail": "http://books.google.com/books/content?id=lJaXQgAACAAJ&printsec=frontcover&img=1&zoom=1&source=gbs_api"}, "authors": ["Kevin Lane Keller"], "ratingsCount": 4, "allowAnonLogging": false, "infoLink": "http://books.google.com/books?id=lJaXQgAACAAJ&dq=isbn:0130411507&hl=&source=gbs_api", "categories": ["Business & Economics"], "averageRating": 4.0}, "searchInfo": {"textSnippet": "Incorporating the latest thinking and developments from both academia and industry, this exploration of brands, brand equity and strategic brand management combines a comprehensive theoretical foundation with numerous techniques and ..."}, "saleInfo": {"country": "US", "saleability": "NOT_FOR_SALE", "isEbook": false}, "etag": "Skebrv5g6RE", "accessInfo": {"webReaderLink": "http://books.google.com/books/reader?id=lJaXQgAACAAJ&hl=&printsec=frontcover&output=reader&source=gbs_api", "publicDomain": false, "embeddable": false, "country": "US", "textToSpeechPermission": "ALLOWED", "pdf": {"isAvailable": false}, "quoteSharingAllowed": false, "viewability": "NO_PAGES", "epub": {"isAvailable": false}, "accessViewStatus": "NONE"}, "id": "lJaXQgAACAAJ", "selfLink": "https://www.googleapis.com/books/v1/volumes/lJaXQgAACAAJ"}], "kind": "books#volumes"}