{"totalItems": 1, "items": [{"kind": "books#volume", "volumeInfo": {"publisher": "Courier Corporation", "description": "Written by two recognized experts in the field, this introduction to heat and mass transfer for engineering students has been used in the classroom for over 32 years, and it's been revised and updated regularly. Worked examples and end-of-chapter exercises appear throughout the text, and a separate solutions manual is available to instructors upon request.", "language": "en", "publishedDate": "2011", "readingModes": {"text": false, "image": true}, "previewLink": "http://books.google.com/books?id=P8iV6IjNtI8C&printsec=frontcover&dq=isbn:0486479315&hl=&cd=1&source=gbs_api", "title": "A Heat Transfer Textbook", "printType": "BOOK", "pageCount": 755, "maturityRating": "NOT_MATURE", "contentVersion": "preview-1.0.0", "industryIdentifiers": [{"identifier": "9780486479316", "type": "ISBN_13"}, {"identifier": "0486479315", "type": "ISBN_10"}], "imageLinks": {"smallThumbnail": "http://books.google.com/books/content?id=P8iV6IjNtI8C&printsec=frontcover&img=1&zoom=5&edge=curl&source=gbs_api", "thumbnail": "http://books.google.com/books/content?id=P8iV6IjNtI8C&printsec=frontcover&img=1&zoom=1&edge=curl&source=gbs_api"}, "authors": ["John H. Lienhard"], "allowAnonLogging": false, "infoLink": "http://books.google.com/books?id=P8iV6IjNtI8C&dq=isbn:0486479315&hl=&source=gbs_api", "categories": ["Science"], "canonicalVolumeLink": "http://books.google.com/books/about/A_Heat_Transfer_Textbook.html?hl=&id=P8iV6IjNtI8C"}, "searchInfo": {"textSnippet": "Worked examples and end-of-chapter exercises appear throughout the text, and a separate solutions manual is available to instructors upon request."}, "saleInfo": {"country": "US", "saleability": "NOT_FOR_SALE", "isEbook": false}, "etag": "tsqU6AdcyJ4", "accessInfo": {"webReaderLink": "http://books.google.com/books/reader?id=P8iV6IjNtI8C&hl=&printsec=frontcover&output=reader&source=gbs_api", "publicDomain": false, "embeddable": true, "country": "US", "textToSpeechPermission": "ALLOWED", "pdf": {"isAvailable": false}, "quoteSharingAllowed": false, "viewability": "PARTIAL", "epub": {"isAvailable": false}, "accessViewStatus": "SAMPLE"}, "id": "P8iV6IjNtI8C", "selfLink": "https://www.googleapis.com/books/v1/volumes/P8iV6IjNtI8C"}], "kind": "books#volumes"}